MANIFEST.in
README.md
setup.cfg
setup.py
docs/Makefile
docs/conf.py
docs/index.rst
docs/installation.rst
docs/make.bat
docs/usage.rst
pkgversion/__init__.py
pkgversion/pkgversion.py
py_pkgversion.egg-info/PKG-INFO
py_pkgversion.egg-info/SOURCES.txt
py_pkgversion.egg-info/dependency_links.txt
py_pkgversion.egg-info/not-zip-safe
py_pkgversion.egg-info/top_level.txt
tests/__init__.py
tests/test_pkgversion.py
tests/fixtures/requirements.txt