Metadata-Version: 1.1
Name: py-pkgversion
Version: 1.0.2
Summary: Versioning utils for python projects
Home-page: https://github.com/kpn-digital/py-pkgversion
Author: Niels Lensink
Author-email: niels@elements.nl
License: UNKNOWN
Platform: UNKNOWN
Classifier: Development Status :: 5 - Production/Stable
Classifier: Environment :: Web Environment
Classifier: Intended Audience :: Developers
Classifier: Operating System :: OS Independent
Classifier: Programming Language :: Python
Classifier: Programming Language :: Python :: 2
Classifier: Programming Language :: Python :: 2.7
Classifier: Topic :: Internet :: WWW/HTTP
